{
"type": "FeatureCollection",
"name": "Praktik Dokter",
"crs": { "type": "name", "properties": { "name": "urn:ogc:def:crs:OGC:1.3:CRS84" } },
"features": [
{ "type": "Feature", "properties": { "Id": 0 }, "geometry": { "type": "Point", "coordinates": [ 101.389118046093728, 0.484490313040571 ] } },
{ "type": "Feature", "properties": { "Id": 0 }, "geometry": { "type": "Point", "coordinates": [ 101.389879473615593, 0.470499082326288 ] } },
{ "type": "Feature", "properties": { "Id": 0 }, "geometry": { "type": "Point", "coordinates": [ 101.35599594889257, 0.472593008011419 ] } },
{ "type": "Feature", "properties": { "Id": 0 }, "geometry": { "type": "Point", "coordinates": [ 101.360469335583531, 0.493437086422493 ] } },
{ "type": "Feature", "properties": { "Id": 0 }, "geometry": { "type": "Point", "coordinates": [ 101.344193822303652, 0.473925506174684 ] } },
{ "type": "Feature", "properties": { "Id": 0 }, "geometry": { "type": "Point", "coordinates": [ 101.408553268698412, 0.448723965068737 ] } },
{ "type": "Feature", "properties": { "Id": 0 }, "geometry": { "type": "Point", "coordinates": [ 101.404984077189667, 0.457646943840601 ] } },
{ "type": "Feature", "properties": { "Id": 0 }, "geometry": { "type": "Point", "coordinates": [ 101.417357274419984, 0.458122836041767 ] } },
{ "type": "Feature", "properties": { "Id": 0 }, "geometry": { "type": "Point", "coordinates": [ 101.394930854440034, 0.438670742319104 ] } },
{ "type": "Feature", "properties": { "Id": 0 }, "geometry": { "type": "Point", "coordinates": [ 101.403377941010731, 0.436945633089877 ] } },
{ "type": "Feature", "properties": { "Id": 0 }, "geometry": { "type": "Point", "coordinates": [ 101.393146258685661, 0.451995723951754 ] } },
{ "type": "Feature", "properties": { "Id": 0 }, "geometry": { "type": "Point", "coordinates": [ 101.385716738699685, 0.451971830197489 ] } },
{ "type": "Feature", "properties": { "Id": 0 }, "geometry": { "type": "Point", "coordinates": [ 101.35844811557287, 0.460180970667603 ] } },
{ "type": "Feature", "properties": { "Id": 0 }, "geometry": { "type": "Point", "coordinates": [ 101.390570839151579, 0.464178465157398 ] } },
{ "type": "Feature", "properties": { "Id": 0 }, "geometry": { "type": "Point", "coordinates": [ 101.402285223115882, 0.495621852618931 ] } },
{ "type": "Feature", "properties": { "Id": 0 }, "geometry": { "type": "Point", "coordinates": [ 101.399072950758011, 0.484259926316091 ] } },
{ "type": "Feature", "properties": { "Id": 0 }, "geometry": { "type": "Point", "coordinates": [ 101.402820601842194, 0.470042646806255 ] } }
]
}
