{
"type": "FeatureCollection",
"name": "Puskesmas",
"crs": { "type": "name", "properties": { "name": "urn:ogc:def:crs:OGC:1.3:CRS84" } },
"features": [
{ "type": "Feature", "properties": { "Id": 0 }, "geometry": { "type": "Point", "coordinates": [ 101.381057810936113, 0.487673311556567 ] } },
{ "type": "Feature", "properties": { "Id": 0 }, "geometry": { "type": "Point", "coordinates": [ 101.409515975566208, 0.476084867037474 ] } },
{ "type": "Feature", "properties": { "Id": 0 }, "geometry": { "type": "Point", "coordinates": [ 101.406797441367047, 0.485025691766882 ] } }
]
}
