{
"type": "FeatureCollection",
"name": "Renang",
"crs": { "type": "name", "properties": { "name": "urn:ogc:def:crs:OGC:1.3:CRS84" } },
"features": [
{ "type": "Feature", "properties": { "Id": 0 }, "geometry": { "type": "Point", "coordinates": [ 101.382584822825052, 0.482583974146819 ] } },
{ "type": "Feature", "properties": { "Id": 0 }, "geometry": { "type": "Point", "coordinates": [ 101.404375331851199, 0.446118377313326 ] } },
{ "type": "Feature", "properties": { "Id": 0 }, "geometry": { "type": "Point", "coordinates": [ 101.397579591218545, 0.448345552814783 ] } },
{ "type": "Feature", "properties": { "Id": 0 }, "geometry": { "type": "Point", "coordinates": [ 101.382863814627996, 0.448345552814786 ] } },
{ "type": "Feature", "properties": { "Id": 0 }, "geometry": { "type": "Point", "coordinates": [ 101.37144240180001, 0.449601908225865 ] } },
{ "type": "Feature", "properties": { "Id": 0 }, "geometry": { "type": "Point", "coordinates": [ 101.406782156658608, 0.468224164922729 ] } },
{ "type": "Feature", "properties": { "Id": 0 }, "geometry": { "type": "Point", "coordinates": [ 101.409435255680094, 0.483143385429286 ] } },
{ "type": "Feature", "properties": { "Id": 0 }, "geometry": { "type": "Point", "coordinates": [ 101.400631249958536, 0.47915778824452 ] } }
]
}
